qingqing.py
WJK-1.0.dist-info/METADATA
WJK-1.0.dist-info/WHEEL
WJK-1.0.dist-info/top_level.txt
WJK-1.0.dist-info/RECORD
