Metadata-Version: 2.1
Name: WJK
Version: 1.0
Summary: 庆庆
Home-page: UNKNOWN
Author: 庆庆
Author-email: 1607210015@qq.com
License: UNKNOWN
Platform: UNKNOWN
